pioreactor_air_bubbler/__init__.py
pioreactor_air_bubbler/additional_config.ini
pioreactor_air_bubbler/ui/contrib/jobs/pioreactor_bubbler.yaml
pioreactor_air_bubbler-0.11.0.dist-info/licenses/LICENSE
pioreactor_air_bubbler-0.11.0.dist-info/METADATA
pioreactor_air_bubbler-0.11.0.dist-info/WHEEL
pioreactor_air_bubbler-0.11.0.dist-info/entry_points.txt
pioreactor_air_bubbler-0.11.0.dist-info/top_level.txt
pioreactor_air_bubbler-0.11.0.dist-info/RECORD
