Metadata-Version: 2.4
Name: pioreactor-air-bubbler
Version: 0.11.0
Summary: Add an air bubbler to your Pioreactor as a background job
Home-page: https://github.com/Pioreactor/pioreactor-air-bubbler
Author: Pioreactor
Author-email: hello@pioreactor.com
License: MIT
License-File: LICENSE
Dynamic: author
Dynamic: author-email
Dynamic: description
Dynamic: description-content-type
Dynamic: home-page
Dynamic: license
Dynamic: license-file
Dynamic: summary
